[
  {
    "nombre": "The Psychology of Money",
    "descripcion": "Libro claro y muy usable para entender hábitos, sesgos y decisiones emocionales alrededor del dinero.",
    "imagen": "/assets/recursos/recurso-libros.jpg",
    "imagen_alt": "Escritorio con laptop y libros apilados",
    "link_afiliado": "https://www.amazon.com/dp/0857197681?tag=minutofinanci-20",
    "categoria": "Finanzas personales"
  },
  {
    "nombre": "I Will Teach You to Be Rich",
    "descripcion": "Guía práctica para automatizar finanzas, ordenar gastos, ahorrar e invertir con un sistema simple.",
    "imagen": "/assets/recursos/recurso-libros.jpg",
    "imagen_alt": "Escritorio con laptop y libros apilados",
    "link_afiliado": "https://www.amazon.com/dp/1523505745?tag=minutofinanci-20",
    "categoria": "Ahorro y hábitos"
  },
  {
    "nombre": "Your Money or Your Life",
    "descripcion": "Un clásico para repensar la relación con el dinero, el consumo, el ahorro y la independencia financiera.",
    "imagen": "/assets/recursos/recurso-presupuesto.jpg",
    "imagen_alt": "Notebook abierto con calculadora y lapicera en un escritorio",
    "link_afiliado": "https://www.amazon.com/dp/0143115766?tag=minutofinanci-20",
    "categoria": "Presupuesto"
  },
  {
    "nombre": "The Simple Path to Wealth",
    "descripcion": "Introducción directa a inversión de largo plazo, independencia financiera y fondos indexados.",
    "imagen": "/assets/recursos/recurso-inversion.jpg",
    "imagen_alt": "Pantalla con gráficos y visualizaciones de datos financieros",
    "link_afiliado": "https://www.amazon.com/dp/1533667926?tag=minutofinanci-20",
    "categoria": "Inversión básica"
  },
  {
    "nombre": "The Bogleheads' Guide to Investing",
    "descripcion": "Manual práctico para construir una cartera diversificada, simple y de bajo costo.",
    "imagen": "/assets/recursos/recurso-inversion.jpg",
    "imagen_alt": "Pantalla con gráficos y visualizaciones de datos financieros",
    "link_afiliado": "https://www.amazon.com/dp/0470067365?tag=minutofinanci-20",
    "categoria": "Inversión indexada"
  },
  {
    "nombre": "Just Keep Buying",
    "descripcion": "Libro moderno con datos y reglas simples para ahorrar, invertir y sostener el plan en el tiempo.",
    "imagen": "/assets/recursos/recurso-inversion.jpg",
    "imagen_alt": "Pantalla con gráficos y visualizaciones de datos financieros",
    "link_afiliado": "https://www.amazon.com/dp/0857199714?tag=minutofinanci-20",
    "categoria": "Ahorro e inversión"
  },
  {
    "nombre": "Clever Fox Budget Planner",
    "descripcion": "Planner físico para armar presupuesto mensual, registrar gastos, metas y seguimiento de hábitos.",
    "imagen": "/assets/recursos/recurso-presupuesto.jpg",
    "imagen_alt": "Notebook abierto con calculadora y lapicera en un escritorio",
    "link_afiliado": "https://www.amazon.com/dp/B084RP9DBC?tag=minutofinanci-20",
    "categoria": "Organización"
  },
  {
    "nombre": "Texas Instruments BA II Plus",
    "descripcion": "Calculadora financiera popular para practicar valor del dinero en el tiempo, tasas, cuotas y flujos.",
    "imagen": "/assets/recursos/recurso-calculadora.jpg",
    "imagen_alt": "Calculadora financiera HP sobre fondo claro",
    "link_afiliado": "https://www.amazon.com/dp/B00000JZKB?tag=minutofinanci-20",
    "categoria": "Herramientas"
  }
]
